tensorneko_tool/__init__.py
tensorneko_tool/__main__.py
tensorneko_tool/dep_check.py
tensorneko_tool/gotify.py
tensorneko_tool/utils.py
tensorneko_tool/version.txt
tensorneko_tool-0.3.22.dist-info/licenses/LICENSE
tensorneko_tool-0.3.22.dist-info/METADATA
tensorneko_tool-0.3.22.dist-info/WHEEL
tensorneko_tool-0.3.22.dist-info/entry_points.txt
tensorneko_tool-0.3.22.dist-info/top_level.txt
tensorneko_tool-0.3.22.dist-info/RECORD
